diffpy/__init__.py
diffpy/structure/__init__.py
diffpy/structure/_legacy_importer.py
diffpy/structure/atom.py
diffpy/structure/lattice.py
diffpy/structure/mmlibspacegroups.py
diffpy/structure/pdffitstructure.py
diffpy/structure/sgtbxspacegroups.py
diffpy/structure/spacegroupmod.py
diffpy/structure/spacegroups.py
diffpy/structure/structure.py
diffpy/structure/structureerrors.py
diffpy/structure/symmetryutilities.py
diffpy/structure/utils.py
diffpy/structure/version.py
diffpy/structure/apps/__init__.py
diffpy/structure/apps/anyeye.py
diffpy/structure/apps/transtru.py
diffpy/structure/expansion/__init__.py
diffpy/structure/expansion/makeellipsoid.py
diffpy/structure/expansion/shapeutils.py
diffpy/structure/expansion/supercell_mod.py
diffpy/structure/parsers/__init__.py
diffpy/structure/parsers/p_auto.py
diffpy/structure/parsers/p_cif.py
diffpy/structure/parsers/p_discus.py
diffpy/structure/parsers/p_pdb.py
diffpy/structure/parsers/p_pdffit.py
diffpy/structure/parsers/p_rawxyz.py
diffpy/structure/parsers/p_xcfg.py
diffpy/structure/parsers/p_xyz.py
diffpy/structure/parsers/parser_index_mod.py
diffpy/structure/parsers/structureparser.py
diffpy_structure-3.3.1.dist-info/licenses/AUTHORS.rst
diffpy_structure-3.3.1.dist-info/licenses/LICENSE-DANSE.rst
diffpy_structure-3.3.1.dist-info/licenses/LICENSE-pymmlib.rst
diffpy_structure-3.3.1.dist-info/licenses/LICENSE.rst
diffpy_structure-3.3.1.dist-info/METADATA
diffpy_structure-3.3.1.dist-info/WHEEL
diffpy_structure-3.3.1.dist-info/entry_points.txt
diffpy_structure-3.3.1.dist-info/top_level.txt
diffpy_structure-3.3.1.dist-info/RECORD
